trashPandasdf/__init__.py
trashPandasdf/froude_scale.py
trashPandasdf/test_trashPandas.py
trashPandasdf/trashPandas.py
trashpandasdf-0.0.2.dist-info/METADATA
trashpandasdf-0.0.2.dist-info/WHEEL
trashpandasdf-0.0.2.dist-info/licenses/LICENSE
trashpandasdf-0.0.2.dist-info/RECORD
