Metadata-Version: 2.3
Name: trashPandasdf
Version: 0.0.2
Summary: A version of pandas dataframe that adds a lot of functionnalities
Project-URL: Homepage, https://github.com
Project-URL: Issues, https://github.com
Author-email: Maximilien André <maximilien.andre@ec-nantes.fr>
License-File: LICENSE
Classifier: License :: OSI Approved :: MIT License
Classifier: Operating System :: OS Independent
Classifier: Programming Language :: Python :: 3
Requires-Python: >=3.10
